odoo/addons/l10n_fr_siret/README.rst
odoo/addons/l10n_fr_siret/__init__.py
odoo/addons/l10n_fr_siret/__manifest__.py
odoo/addons/l10n_fr_siret/post_install.py
odoo/addons/l10n_fr_siret/demo/partner_demo.xml
odoo/addons/l10n_fr_siret/i18n/bg.po
odoo/addons/l10n_fr_siret/i18n/cs_CZ.po
odoo/addons/l10n_fr_siret/i18n/da.po
odoo/addons/l10n_fr_siret/i18n/de.po
odoo/addons/l10n_fr_siret/i18n/el_GR.po
odoo/addons/l10n_fr_siret/i18n/es.po
odoo/addons/l10n_fr_siret/i18n/es_MX.po
odoo/addons/l10n_fr_siret/i18n/fi.po
odoo/addons/l10n_fr_siret/i18n/fr.po
odoo/addons/l10n_fr_siret/i18n/fr_CH.po
odoo/addons/l10n_fr_siret/i18n/hr.po
odoo/addons/l10n_fr_siret/i18n/it.po
odoo/addons/l10n_fr_siret/i18n/l10n_fr_siret.pot
odoo/addons/l10n_fr_siret/i18n/nb_NO.po
odoo/addons/l10n_fr_siret/i18n/nl.po
odoo/addons/l10n_fr_siret/i18n/pt.po
odoo/addons/l10n_fr_siret/i18n/pt_BR.po
odoo/addons/l10n_fr_siret/i18n/sl.po
odoo/addons/l10n_fr_siret/models/__init__.py
odoo/addons/l10n_fr_siret/models/res_company.py
odoo/addons/l10n_fr_siret/models/res_partner.py
odoo/addons/l10n_fr_siret/readme/CONTRIBUTORS.md
odoo/addons/l10n_fr_siret/readme/DESCRIPTION.md
odoo/addons/l10n_fr_siret/readme/INSTALL.md
odoo/addons/l10n_fr_siret/readme/USAGE.md
odoo/addons/l10n_fr_siret/static/description/icon.png
odoo/addons/l10n_fr_siret/static/description/index.html
odoo/addons/l10n_fr_siret/static/description/partner_duplicate_warning.png
odoo/addons/l10n_fr_siret/tests/__init__.py
odoo/addons/l10n_fr_siret/tests/test_fr_siret.py
odoo/addons/l10n_fr_siret/views/res_company.xml
odoo/addons/l10n_fr_siret/views/res_partner.xml
odoo_addon_l10n_fr_siret-18.0.1.2.0.2.dist-info/METADATA
odoo_addon_l10n_fr_siret-18.0.1.2.0.2.dist-info/WHEEL
odoo_addon_l10n_fr_siret-18.0.1.2.0.2.dist-info/top_level.txt
odoo_addon_l10n_fr_siret-18.0.1.2.0.2.dist-info/RECORD
