Metadata-Version: 2.1
Name: odoo-addon-l10n_fr_siret
Version: 18.0.1.2.0.2
Requires-Python: >=3.10
Requires-Dist: odoo-addon-base_view_inheritance_extension==18.0.*
Requires-Dist: odoo==18.0.*
Requires-Dist: python-stdnum
Summary: Complete support for SIRET/SIREN/NIC with checksum validation
Home-page: https://github.com/OCA/l10n-france
License: AGPL-3
Author: =?utf-8?q?Num=C3=A9rigraphe=2CAkretion=2COdoo_Community_Association_=28OCA=29?=
Author-email: support@odoo-community.org
Classifier: Programming Language :: Python
Classifier: Framework :: Odoo
Classifier: Framework :: Odoo :: 18.0
Classifier: License :: OSI Approved :: GNU Affero General Public License v3
Classifier: Development Status :: 6 - Mature
